accuhit/__init__.py
accuhit/utils/__init__.py
accuhit/utils/application_exception.py
accuhit/utils/aws_s3.py
accuhit/utils/check_headers.py
accuhit/utils/datetime.py
accuhit/utils/error_code.py
accuhit/utils/exceptions.py
accuhit/utils/files.py
accuhit/utils/page.py
accuhit/utils/payload.py
accuhit/utils/regex.py
accuhit/utils/validator.py
accuhit_pyutils-0.9.0.dist-info/METADATA
accuhit_pyutils-0.9.0.dist-info/WHEEL
accuhit_pyutils-0.9.0.dist-info/top_level.txt
accuhit_pyutils-0.9.0.dist-info/RECORD
