Metadata-Version: 2.1
Name: accuhit-pyutils
Version: 0.9.0
Summary: accuhit deeplearning library
Author: accuhit
Author-email: developer@accuhit.net
License: Copyright accuhit
Classifier: Development Status :: 4 - Beta
Classifier: Intended Audience :: Developers
Classifier: Operating System :: OS Independent
Classifier: Programming Language :: Python :: 3
Classifier: Programming Language :: Python :: 3.8
Classifier: Programming Language :: Python :: 3.11
Requires-Dist: pytz ==2024.1
Requires-Dist: pandas >=0.23.4
Requires-Dist: boto3 ~=1.34.74
Requires-Dist: botocore ~=1.34.74
Requires-Dist: python-dateutil ==2.9.0.post0
Requires-Dist: Werkzeug >=0.14.1
Requires-Dist: pymongo ~=4.6.2
